dhosredis/__init__.py
dhosredis/redis.py
dhosredis/stub_redis.py
dhos_redis-1.0.2.dist-info/LICENSE.md
dhos_redis-1.0.2.dist-info/WHEEL
dhos_redis-1.0.2.dist-info/METADATA
dhos_redis-1.0.2.dist-info/RECORD
