Metadata-Version: 2.1
Name: dhos-redis
Version: 1.0.2
Summary: Redis functionality for Polaris
Home-page: https://github.com/polaris-foundation/dhos-redis
Keywords: Polaris,Redis,Cache
Author: Jon Daly
Author-email: jonathan.daly@sensynehealth.com
Requires-Python: >=3.8,<4.0
Classifier: Programming Language :: Python :: 3
Classifier: Programming Language :: Python :: 3.10
Classifier: Programming Language :: Python :: 3.8
Classifier: Programming Language :: Python :: 3.9
Requires-Dist: environs (>=9.0.0,<10.0.0)
Requires-Dist: redis (>=3.0.0,<4.0.0)
Requires-Dist: she-logging (>=1.0.0,<2.0.0)
Project-URL: Repository, https://github.com/polaris-foundation/dhos-redis
